Metadata-Version: 2.1
Name: gradio_notebook
Version: 0.0.16
Summary: Notebook for interacting with models in AIConfig
Author: LastMile AI
License-Expression: MIT
License-File: LICENSE
Keywords: aiconfig,gradio-custom-component,gradio-template-Fallback,notebook,workbook
Requires-Python: >=3.10
Requires-Dist: aiconfig-extension-hugging-face>=0.0.13
Requires-Dist: asyncio
Requires-Dist: boto3
Requires-Dist: botocore
Requires-Dist: gradio<5.0,>=4.0
Requires-Dist: python-aiconfig>=1.1.30
Requires-Dist: requests
Provides-Extra: dev
Requires-Dist: build; extra == 'dev'
Requires-Dist: twine; extra == 'dev'
